{
  "multipart": [
    {"apply": {"model": "bb:block/frames/frame_base"}},
    {"when": {"north": "true"},
    "apply": {"model": "bb:block/frames/frame_connector_bottom", "uvlock":  true}
    },
    {"when": {"north": "true"},
      "apply": {"model": "bb:block/frames/frame_connector_top", "uvlock":  true}
    },
    {"when": {"north": "true", "plywood": true},
      "apply": {"model": "bb:block/frames/frame_full_plywood_half_left","y": 90, "uvlock":  true}
    },
    {"when": {"north": "true", "plywood": true},
      "apply": {"model": "bb:block/frames/frame_full_plywood_half_right","y": 270, "uvlock":  true}
    },
    {"when": {"south": "true"},
      "apply": {"model": "bb:block/frames/frame_connector_bottom","y": 180, "uvlock":  true}
    },
    {"when": {"south": "true"},
      "apply": {"model": "bb:block/frames/frame_connector_top","y": 180, "uvlock":  true}
    },
    {"when": {"south": "true", "plywood": true},
      "apply": {"model": "bb:block/frames/frame_full_plywood_half_right","y": 90, "uvlock":  true}
    },
    {"when": {"south": "true", "plywood": true},
      "apply": {"model": "bb:block/frames/frame_full_plywood_half_left","y": 270, "uvlock":  true}
    },
    {"when": {"east": "true"},
      "apply": {"model": "bb:block/frames/frame_connector_bottom","y": 90, "uvlock":  true}
    },
    {"when": {"east": "true"},
      "apply": {"model": "bb:block/frames/frame_connector_top","y": 90, "uvlock":  true}
    },
    {"when": {"east": "true", "plywood": true},
      "apply": {"model": "bb:block/frames/frame_full_plywood_half_left","y": 180, "uvlock":  true}
    },
    {"when": {"east": "true", "plywood": true},
      "apply": {"model": "bb:block/frames/frame_full_plywood_half_right", "uvlock":  true}
    },
    {"when": {"west": "true"},
      "apply": {"model": "bb:block/frames/frame_connector_bottom","y": 270, "uvlock":  true}
    },
    {"when": {"west": "true"},
      "apply": {"model": "bb:block/frames/frame_connector_top","y": 270, "uvlock":  true}
    },
    {"when": {"west": "true", "plywood": true},
      "apply": {"model": "bb:block/frames/frame_full_plywood_half_left", "uvlock":  true}
    },
    {"when": {"west": "true", "plywood": true},
      "apply": {"model": "bb:block/frames/frame_full_plywood_half_right","y": 180, "uvlock":  true}
    }
  ]
}